bfabric_web_apps/__init__.py
bfabric_web_apps/layouts/layouts.py
bfabric_web_apps/objects/BfabricInterface.py
bfabric_web_apps/objects/Logger.py
bfabric_web_apps/utils/app_init.py
bfabric_web_apps/utils/callbacks.py
bfabric_web_apps/utils/charging.py
bfabric_web_apps/utils/components.py
bfabric_web_apps/utils/config.py
bfabric_web_apps/utils/create_app_in_bfabric.py
bfabric_web_apps/utils/dataset_utils.py
bfabric_web_apps/utils/get_logger.py
bfabric_web_apps/utils/get_power_user_wrapper.py
bfabric_web_apps/utils/redis_connection.py
bfabric_web_apps/utils/redis_queue.py
bfabric_web_apps/utils/redis_worker_init.py
bfabric_web_apps/utils/resource_utilities.py
bfabric_web_apps/utils/run_main_pipeline.py
bfabric_web_apps/utils/url_utils.py
bfabric_web_apps-0.3.0.dist-info/LICENSE
bfabric_web_apps-0.3.0.dist-info/METADATA
bfabric_web_apps-0.3.0.dist-info/WHEEL
bfabric_web_apps-0.3.0.dist-info/RECORD
