Metadata-Version: 2.1
Name: bfabric-web-apps
Version: 0.3.0
Summary: A package containing handy boilerplate utilities for developing bfabric web-applications
Home-page: https://gitlab.bfabric.org/bfabricpublic/bfabric-web-apps/-/wikis/home/
License: MIT
Keywords: bfabric,lims,dash,web-apps,laboratory,bioinformatics
Author: Marc Zuber, Griffin White, GWC GmbH
Requires-Python: >=3.10,<4.0
Classifier: Development Status :: 4 - Beta
Classifier: Framework :: Dash
Classifier: Intended Audience :: Developers
Classifier: Intended Audience :: Science/Research
Classifier: License :: OSI Approved :: MIT License
Classifier: Programming Language :: Python :: 3
Classifier: Programming Language :: Python :: 3.10
Classifier: Programming Language :: Python :: 3.11
Classifier: Programming Language :: Python :: 3.12
Classifier: Topic :: Scientific/Engineering :: Bio-Informatics
Requires-Dist: bfabric (>=1.13.36,<2.0.0)
Requires-Dist: dash (>=3.0.2,<4.0.0)
Requires-Dist: dash-bootstrap-components (>=2.0.0,<3.0.0)
Requires-Dist: dash-daq (>=0.6.0,<0.7.0)
Requires-Dist: pydantic-settings (>=2.8.1,<3.0.0)
Requires-Dist: pydantic[email] (>=2.10.6,<3.0.0)
Requires-Dist: rq (==1.15.1)
Project-URL: Repository, https://gitlab.bfabric.org/bfabricpublic/bfabric-web-apps
